CHANGELOG.txt
LICENSE.txt
MANIFEST.in
README.txt
how_to_change_pypi.txt
requirements.txt
setup.py
docs/conf.py
docs/_sources/api.rst.txt
docs/_sources/index.rst.txt
docs/_sources/modules.rst.txt
docs/_sources/setup.rst.txt
docs/_sources/treetopper.rst.txt
docs/_sources/api/treetopper._console_print.rst.txt
docs/_sources/api/treetopper._constants.rst.txt
docs/_sources/api/treetopper._import_from_sheets.rst.txt
docs/_sources/api/treetopper._pdf_print.rst.txt
docs/_sources/api/treetopper._testing.rst.txt
docs/_sources/api/treetopper.blank_sheet.rst.txt
docs/_sources/api/treetopper.fvs.rst.txt
docs/_sources/api/treetopper.log.rst.txt
docs/_sources/api/treetopper.plot.rst.txt
docs/_sources/api/treetopper.rst.txt
docs/_sources/api/treetopper.stand.rst.txt
docs/_sources/api/treetopper.thin.rst.txt
docs/_sources/api/treetopper.timber.rst.txt
docs/_sources/api_private/treetopper._console_print.rst.txt
docs/_sources/api_private/treetopper._constants.rst.txt
docs/_sources/api_private/treetopper._import_from_sheets.rst.txt
docs/_sources/api_private/treetopper._pdf_print.rst.txt
docs/_sources/api_private/treetopper._testing.rst.txt
docs/_sources/api_private/treetopper.rst.txt
treetopper/__init__.py
treetopper/_constants.py
treetopper/_exceptions.py
treetopper/_import_from_sheets.py
treetopper/_print_console.py
treetopper/_print_pdf.py
treetopper/_utils.py
treetopper/blank_sheet.py
treetopper/del_test.py
treetopper/fvs.py
treetopper/log.py
treetopper/plot.py
treetopper/stand.py
treetopper/thin.py
treetopper/timber.py
treetopper.egg-info/PKG-INFO
treetopper.egg-info/SOURCES.txt
treetopper.egg-info/dependency_links.txt
treetopper.egg-info/requires.txt
treetopper.egg-info/top_level.txt
treetopper/example_csv_and_xlsx/Example_CSV_full.csv
treetopper/example_csv_and_xlsx/Example_CSV_quick.csv
treetopper/example_csv_and_xlsx/Example_Excel_full.xlsx
treetopper/example_csv_and_xlsx/Example_Excel_quick.xlsx
venv/Lib/site-packages/jdcal.py
venv/Lib/site-packages/pythoncom.py
venv/Lib/site-packages/pywin32.version.txt
venv/Lib/site-packages/_distutils_hack/__init__.py
venv/Lib/site-packages/_distutils_hack/override.py
venv/Lib/site-packages/et_xmlfile-1.1.0.dist-info/AUTHORS.txt
venv/Lib/site-packages/et_xmlfile-1.1.0.dist-info/top_level.txt
venv/Lib/site-packages/fpdf-1.7.2.dist-info/top_level.txt
venv/Lib/site-packages/jdcal-1.4.1.dist-info/LICENSE.txt
venv/Lib/site-packages/jdcal-1.4.1.dist-info/top_level.txt
venv/Lib/site-packages/openpyxl-3.0.6.dist-info/top_level.txt
venv/Lib/site-packages/pip-21.1.2.dist-info/LICENSE.txt
venv/Lib/site-packages/pip-21.1.2.dist-info/entry_points.txt
venv/Lib/site-packages/pip-21.1.2.dist-info/top_level.txt
venv/Lib/site-packages/pyodbc-4.0.30.dist-info/LICENSE.txt
venv/Lib/site-packages/pyodbc-4.0.30.dist-info/top_level.txt
venv/Lib/site-packages/pywin32-301.dist-info/top_level.txt
venv/Lib/site-packages/setuptools-57.0.0.dist-info/dependency_links.txt
venv/Lib/site-packages/setuptools-57.0.0.dist-info/entry_points.txt
venv/Lib/site-packages/setuptools-57.0.0.dist-info/top_level.txt
