Metadata-Version: 2.1
Name: treetopper
Version: 1.1.6
Summary: Python module for calculating Timber data from tree species of the west coast
Home-page: https://github.com/zacharybeebe/treetopper
Author: Zach Beebe
Author-email: z.beebe@yahoo.com
License: MIT
Keywords: forestry,natural resources,natural,resources,forest,environmental,environmental science,science,timber,tree,trees,west,coast,west coast,logging,cruising,scaling,inventory,forests,board feet,cubic feet,DBH,diameter at breast height,DIB,diameter inside bark,RD,relative density,HDR,height to diameter ratio,species,VBAR,volume to basal area ratio,BA,basal area,TPA,trees per acre,scribner,timber marketing,forest marketing,timber management,forest management
Platform: UNKNOWN
Classifier: Development Status :: 5 - Production/Stable
Classifier: Intended Audience :: Science/Research
Classifier: Programming Language :: Python :: 3
Classifier: License :: OSI Approved :: MIT License
Classifier: Operating System :: OS Independent
Requires-Python: >=3.6
License-File: LICENSE.txt
